{
  "id": 2025020183,
  "season": 20252026,
  "gameType": 2,
  "limitedScoring": false,
  "gameDate": "2025-11-01",
  "venue": {
    "default": "Bridgestone Arena"
  },
  "venueLocation": {
    "default": "Nashville"
  },
  "startTimeUTC": "2025-11-01T19:30:00Z",
  "easternUTCOffset": "-04:00",
  "venueUTCOffset": "-05:00",
  "venueTimezone": "US/Central",
  "periodDescriptor": {
    "number": 3,
    "periodType": "REG",
    "maxRegulationPeriods": 3
  },
  "tvBroadcasts": [
    {
      "id": 284,
      "market": "N",
      "countryCode": "CA",
      "network": "SN1",
      "sequenceNumber": 102
    },
    {
      "id": 561,
      "market": "H",
      "countryCode": "US",
      "network": "FDSNSO",
      "sequenceNumber": 277
    }
  ],
  "gameState": "OFF",
  "gameScheduleState": "OK",
  "awayTeam": {
    "id": 20,
    "commonName": {
      "default": "Flames"
    },
    "abbrev": "CGY",
    "placeName": {
      "default": "Calgary"
    },
    "placeNameWithPreposition": {
      "default": "Calgary",
      "fr": "de Calgary"
    },
    "score": 2,
    "sog": 35,
    "logo": "https://assets.nhle.com/logos/nhl/svg/CGY_light.svg",
    "darkLogo": "https://assets.nhle.com/logos/nhl/svg/CGY_dark.svg"
  },
  "homeTeam": {
    "id": 18,
    "commonName": {
      "default": "Predators"
    },
    "abbrev": "NSH",
    "placeName": {
      "default": "Nashville"
    },
    "placeNameWithPreposition": {
      "default": "Nashville",
      "fr": "de Nashville"
    },
    "score": 4,
    "sog": 24,
    "logo": "https://assets.nhle.com/logos/nhl/svg/NSH_light.svg",
    "darkLogo": "https://assets.nhle.com/logos/nhl/svg/NSH_dark.svg"
  },
  "shootoutInUse": true,
  "maxPeriods": 5,
  "regPeriods": 3,
  "otInUse": true,
  "tiesInUse": false,
  "summary": {
    "scoring": [
      {
        "periodDescriptor": {
          "number": 1,
          "periodType": "REG",
          "maxRegulationPeriods": 3
        },
        "goals": [
          {
            "situationCode": "1551",
            "eventId": 355,
            "strength": "ev",
            "playerId": 8478047,
            "firstName": {
              "default": "Michael"
            },
            "lastName": {
              "default": "Bunting"
            },
            "name": {
              "default": "M. Bunting"
            },
            "teamAbbrev": {
              "default": "NSH"
            },
            "headshot": "https://assets.nhle.com/mugs/nhl/20252026/NSH/8478047.png",
            "highlightClipSharingUrl": "https://nhl.com/video/cgy-nsh-bunting-scores-goal-against-dustin-wolf-6384400728112",
            "highlightClipSharingUrlFr": "https://nhl.com/fr/video/cgy-nsh-bunting-marque-un-but-contre-dustin-wolf-6384399862112",
            "highlightClip": 6384400728112,
            "highlightClipFr": 6384399862112,
            "discreteClip": 6384401320112,
            "discreteClipFr": 6384401315112,
            "goalsToDate": 3,
            "awayScore": 0,
            "homeScore": 1,
            "leadingTeamAbbrev": {
              "default": "NSH"
            },
            "timeInPeriod": "10:29",
            "shotType": "tip-in",
            "goalModifier": "none",
            "assists": [
              {
                "playerId": 8481056,
                "firstName": {
                  "default": "Spencer"
                },
                "lastName": {
                  "default": "Stastney"
                },
                "name": {
                  "default": "S. Stastney"
                },
                "assistsToDate": 4,
                "sweaterNumber": 24
              },
              {
                "playerId": 8482111,
                "firstName": {
                  "default": "Justin"
                },
                "lastName": {
                  "default": "Barron"
                },
                "name": {
                  "default": "J. Barron"
                },
                "assistsToDate": 4,
                "sweaterNumber": 20
              }
            ],
            "pptReplayUrl": "https://wsr.nhle.com/sprites/20252026/2025020183/ev355.json",
            "homeTeamDefendingSide": "left",
            "isHome": true
          },
          {
            "situationCode": "1551",
            "eventId": 364,
            "strength": "ev",
            "playerId": 8484241,
            "firstName": {
              "default": "Matthew"
            },
            "lastName": {
              "default": "Wood"
            },
            "name": {
              "default": "M. Wood"
            },
            "teamAbbrev": {
              "default": "NSH"
            },
            "headshot": "https://assets.nhle.com/mugs/nhl/20252026/NSH/8484241.png",
            "highlightClipSharingUrl": "https://nhl.com/video/cgy-nsh-wood-scores-goal-against-dustin-wolf-6384400541112",
            "highlightClipSharingUrlFr": "https://nhl.com/fr/video/cgy-nsh-wood-marque-un-but-contre-dustin-wolf-6384399864112",
            "highlightClip": 6384400541112,
            "highlightClipFr": 6384399864112,
            "discreteClip": 6384399971112,
            "discreteClipFr": 6384401412112,
            "goalsToDate": 2,
            "awayScore": 0,
            "homeScore": 2,
            "leadingTeamAbbrev": {
              "default": "NSH"
            },
            "timeInPeriod": "11:18",
            "shotType": "wrist",
            "goalModifier": "none",
            "assists": [
              {
                "playerId": 8478047,
                "firstName": {
                  "default": "Michael"
                },
                "lastName": {
                  "default": "Bunting"
                },
                "name": {
                  "default": "M. Bunting"
                },
                "assistsToDate": 3,
                "sweaterNumber": 58
              },
              {
                "playerId": 8483565,
                "firstName": {
                  "default": "Nick"
                },
                "lastName": {
                  "default": "Blankenburg"
                },
                "name": {
                  "default": "N. Blankenburg"
                },
                "assistsToDate": 1,
                "sweaterNumber": 37
              }
            ],
            "pptReplayUrl": "https://wsr.nhle.com/sprites/20252026/2025020183/ev364.json",
            "homeTeamDefendingSide": "left",
            "isHome": true
          },
          {
            "situationCode": "1451",
            "eventId": 468,
            "strength": "pp",
            "playerId": 8476539,
            "firstName": {
              "default": "Jonathan"
            },
            "lastName": {
              "default": "Marchessault"
            },
            "name": {
              "default": "J. Marchessault"
            },
            "teamAbbrev": {
              "default": "NSH"
            },
            "headshot": "https://assets.nhle.com/mugs/nhl/20252026/NSH/8476539.png",
            "highlightClipSharingUrl": "https://nhl.com/video/cgy-nsh-marchessault-scores-ppg-against-dustin-wolf-6384401805112",
            "highlightClipSharingUrlFr": "https://nhl.com/fr/video/cgy-nsh-marchessault-marque-un-but-en-a-n-contre-dustin-wolf-6384399878112",
            "highlightClip": 6384401805112,
            "highlightClipFr": 6384399878112,
            "discreteClip": 6384401137112,
            "discreteClipFr": 6384400837112,
            "goalsToDate": 4,
            "awayScore": 0,
            "homeScore": 3,
            "leadingTeamAbbrev": {
              "default": "NSH"
            },
            "timeInPeriod": "14:17",
            "shotType": "wrist",
            "goalModifier": "none",
            "assists": [
              {
                "playerId": 8478047,
                "firstName": {
                  "default": "Michael"
                },
                "lastName": {
                  "default": "Bunting"
                },
                "name": {
                  "default": "M. Bunting"
                },
                "assistsToDate": 4,
                "sweaterNumber": 58
              },
              {
                "playerId": 8484241,
                "firstName": {
                  "default": "Matthew"
                },
                "lastName": {
                  "default": "Wood"
                },
                "name": {
                  "default": "M. Wood"
                },
                "assistsToDate": 2,
                "sweaterNumber": 71
              }
            ],
            "pptReplayUrl": "https://wsr.nhle.com/sprites/20252026/2025020183/ev468.json",
            "homeTeamDefendingSide": "left",
            "isHome": true
          }
        ]
      },
      {
        "periodDescriptor": {
          "number": 2,
          "periodType": "REG",
          "maxRegulationPeriods": 3
        },
        "goals": []
      },
      {
        "periodDescriptor": {
          "number": 3,
          "periodType": "REG",
          "maxRegulationPeriods": 3
        },
        "goals": [
          {
            "situationCode": "1551",
            "eventId": 959,
            "strength": "ev",
            "playerId": 8476456,
            "firstName": {
              "default": "Jonathan"
            },
            "lastName": {
              "default": "Huberdeau"
            },
            "name": {
              "default": "J. Huberdeau"
            },
            "teamAbbrev": {
              "default": "CGY"
            },
            "headshot": "https://assets.nhle.com/mugs/nhl/20252026/CGY/8476456.png",
            "highlightClipSharingUrl": "https://nhl.com/video/cgy-nsh-huberdeau-scores-goal-against-juuse-saros-6384403575112",
            "highlightClipSharingUrlFr": "https://nhl.com/fr/video/cgy-nsh-huberdeau-marque-un-but-contre-juuse-saros-6384404052112",
            "highlightClip": 6384403575112,
            "highlightClipFr": 6384404052112,
            "discreteClip": 6384403671112,
            "discreteClipFr": 6384402683112,
            "goalsToDate": 2,
            "awayScore": 1,
            "homeScore": 3,
            "leadingTeamAbbrev": {
              "default": "NSH"
            },
            "timeInPeriod": "04:39",
            "shotType": "wrist",
            "goalModifier": "none",
            "assists": [
              {
                "playerId": 8479402,
                "firstName": {
                  "default": "Jake"
                },
                "lastName": {
                  "default": "Bean"
                },
                "name": {
                  "default": "J. Bean"
                },
                "assistsToDate": 1,
                "sweaterNumber": 24
              },
              {
                "playerId": 8482679,
                "firstName": {
                  "default": "Matt"
                },
                "lastName": {
                  "default": "Coronato"
                },
                "name": {
                  "default": "M. Coronato"
                },
                "assistsToDate": 2,
                "sweaterNumber": 27
              }
            ],
            "pptReplayUrl": "https://wsr.nhle.com/sprites/20252026/2025020183/ev959.json",
            "homeTeamDefendingSide": "left",
            "isHome": false
          },
          {
            "situationCode": "1551",
            "eventId": 1055,
            "strength": "ev",
            "playerId": 8480797,
            "firstName": {
              "default": "Joel"
            },
            "lastName": {
              "default": "Farabee"
            },
            "name": {
              "default": "J. Farabee"
            },
            "teamAbbrev": {
              "default": "CGY"
            },
            "headshot": "https://assets.nhle.com/mugs/nhl/20252026/CGY/8480797.png",
            "highlightClipSharingUrl": "https://nhl.com/video/cgy-nsh-farabee-scores-goal-against-juuse-saros-6384404943112",
            "highlightClipSharingUrlFr": "https://nhl.com/fr/video/cgy-nsh-farabee-marque-un-but-contre-juuse-saros-6384404751112",
            "highlightClip": 6384404943112,
            "highlightClipFr": 6384404751112,
            "discreteClip": 6384403869112,
            "discreteClipFr": 6384404939112,
            "goalsToDate": 2,
            "awayScore": 2,
            "homeScore": 3,
            "leadingTeamAbbrev": {
              "default": "NSH"
            },
            "timeInPeriod": "11:57",
            "shotType": "wrist",
            "goalModifier": "none",
            "assists": [
              {
                "playerId": 8475172,
                "firstName": {
                  "default": "Nazem"
                },
                "lastName": {
                  "default": "Kadri"
                },
                "name": {
                  "default": "N. Kadri"
                },
                "assistsToDate": 7,
                "sweaterNumber": 91
              }
            ],
            "pptReplayUrl": "https://wsr.nhle.com/sprites/20252026/2025020183/ev1055.json",
            "homeTeamDefendingSide": "left",
            "isHome": false
          },
          {
            "situationCode": "0651",
            "eventId": 1211,
            "strength": "ev",
            "playerId": 8476887,
            "firstName": {
              "default": "Filip"
            },
            "lastName": {
              "default": "Forsberg"
            },
            "name": {
              "default": "F. Forsberg"
            },
            "teamAbbrev": {
              "default": "NSH"
            },
            "headshot": "https://assets.nhle.com/mugs/nhl/20252026/NSH/8476887.png",
            "highlightClipSharingUrl": "https://nhl.com/video/filip-forsberg-with-a-goal-vs-calgary-flames-6384404179112",
            "highlightClipSharingUrlFr": "https://nhl.com/fr/video/filip-forsberg-with-a-goal-vs-les-flames-de-calgary-6384403502112",
            "highlightClip": 6384404179112,
            "highlightClipFr": 6384403502112,
            "discreteClip": 6384404666112,
            "discreteClipFr": 6384403010112,
            "goalsToDate": 5,
            "awayScore": 2,
            "homeScore": 4,
            "leadingTeamAbbrev": {
              "default": "NSH"
            },
            "timeInPeriod": "19:36",
            "shotType": "backhand",
            "goalModifier": "empty-net",
            "assists": [],
            "pptReplayUrl": "https://wsr.nhle.com/sprites/20252026/2025020183/ev1211.json",
            "homeTeamDefendingSide": "left",
            "isHome": true
          }
        ]
      }
    ],
    "shootout": [],
    "threeStars": [
      {
        "star": 1,
        "playerId": 8478047,
        "teamAbbrev": "NSH",
        "headshot": "https://assets.nhle.com/mugs/nhl/20252026/NSH/8478047.png",
        "name": {
          "default": "M. Bunting"
        },
        "sweaterNo": 58,
        "position": "L",
        "goals": 1,
        "assists": 2,
        "points": 3
      },
      {
        "star": 2,
        "playerId": 8484241,
        "teamAbbrev": "NSH",
        "headshot": "https://assets.nhle.com/mugs/nhl/20252026/NSH/8484241.png",
        "name": {
          "default": "M. Wood"
        },
        "sweaterNo": 71,
        "position": "R",
        "goals": 1,
        "assists": 1,
        "points": 2
      },
      {
        "star": 3,
        "playerId": 8477424,
        "teamAbbrev": "NSH",
        "headshot": "https://assets.nhle.com/mugs/nhl/20252026/NSH/8477424.png",
        "name": {
          "default": "J. Saros"
        },
        "sweaterNo": 74,
        "position": "G",
        "goalsAgainstAverage": 2.0,
        "savePctg": 0.943
      }
    ],
    "penalties": [
      {
        "periodDescriptor": {
          "number": 1,
          "periodType": "REG",
          "maxRegulationPeriods": 3
        },
        "penalties": [
          {
            "timeInPeriod": "02:15",
            "type": "MIN",
            "duration": 2,
            "committedByPlayer": {
              "firstName": {
                "default": "Jake"
              },
              "lastName": {
                "default": "Bean"
              },
              "sweaterNumber": 24
            },
            "teamAbbrev": {
              "default": "CGY"
            },
            "drawnBy": {
              "firstName": {
                "default": "Fedor"
              },
              "lastName": {
                "default": "Svechkov"
              },
              "sweaterNumber": 40
            },
            "descKey": "tripping"
          },
          {
            "timeInPeriod": "13:03",
            "type": "MIN",
            "duration": 2,
            "committedByPlayer": {
              "firstName": {
                "default": "Kevin"
              },
              "lastName": {
                "default": "Bahl"
              },
              "sweaterNumber": 7
            },
            "teamAbbrev": {
              "default": "CGY"
            },
            "drawnBy": {
              "firstName": {
                "default": "Luke"
              },
              "lastName": {
                "default": "Evangelista"
              },
              "sweaterNumber": 77
            },
            "descKey": "elbowing"
          }
        ]
      },
      {
        "periodDescriptor": {
          "number": 2,
          "periodType": "REG",
          "maxRegulationPeriods": 3
        },
        "penalties": [
          {
            "timeInPeriod": "01:07",
            "type": "MIN",
            "duration": 2,
            "committedByPlayer": {
              "firstName": {
                "default": "Morgan"
              },
              "lastName": {
                "default": "Frost"
              },
              "sweaterNumber": 16
            },
            "teamAbbrev": {
              "default": "CGY"
            },
            "drawnBy": {
              "firstName": {
                "default": "Luke"
              },
              "lastName": {
                "default": "Evangelista"
              },
              "sweaterNumber": 77
            },
            "descKey": "high-sticking"
          },
          {
            "timeInPeriod": "10:39",
            "type": "MIN",
            "duration": 2,
            "committedByPlayer": {
              "firstName": {
                "default": "Brayden"
              },
              "lastName": {
                "default": "Pachal"
              },
              "sweaterNumber": 94
            },
            "teamAbbrev": {
              "default": "CGY"
            },
            "drawnBy": {
              "firstName": {
                "default": "Ozzy"
              },
              "lastName": {
                "default": "Wiesblatt"
              },
              "sweaterNumber": 89
            },
            "descKey": "roughing",
            "servedBy": {
              "default": "Samuel Honzek"
            }
          },
          {
            "timeInPeriod": "10:39",
            "type": "MIN",
            "duration": 2,
            "committedByPlayer": {
              "firstName": {
                "default": "Ozzy"
              },
              "lastName": {
                "default": "Wiesblatt"
              },
              "sweaterNumber": 89
            },
            "teamAbbrev": {
              "default": "NSH"
            },
            "drawnBy": {
              "firstName": {
                "default": "Brayden"
              },
              "lastName": {
                "default": "Pachal"
              },
              "sweaterNumber": 94
            },
            "descKey": "roughing"
          },
          {
            "timeInPeriod": "10:39",
            "type": "MIS",
            "duration": 10,
            "committedByPlayer": {
              "firstName": {
                "default": "Brayden"
              },
              "lastName": {
                "default": "Pachal"
              },
              "sweaterNumber": 94
            },
            "teamAbbrev": {
              "default": "CGY"
            },
            "descKey": "misconduct"
          },
          {
            "timeInPeriod": "12:48",
            "type": "MIN",
            "duration": 2,
            "committedByPlayer": {
              "firstName": {
                "default": "Steven"
              },
              "lastName": {
                "default": "Stamkos"
              },
              "sweaterNumber": 91
            },
            "teamAbbrev": {
              "default": "NSH"
            },
            "drawnBy": {
              "firstName": {
                "default": "Mikael"
              },
              "lastName": {
                "default": "Backlund"
              },
              "sweaterNumber": 11
            },
            "descKey": "hooking"
          },
          {
            "timeInPeriod": "17:07",
            "type": "MIN",
            "duration": 2,
            "committedByPlayer": {
              "firstName": {
                "default": "Spencer"
              },
              "lastName": {
                "default": "Stastney"
              },
              "sweaterNumber": 24
            },
            "teamAbbrev": {
              "default": "NSH"
            },
            "drawnBy": {
              "firstName": {
                "default": "Ryan"
              },
              "lastName": {
                "default": "Lomberg"
              },
              "sweaterNumber": 70
            },
            "descKey": "high-sticking"
          }
        ]
      },
      {
        "periodDescriptor": {
          "number": 3,
          "periodType": "REG",
          "maxRegulationPeriods": 3
        },
        "penalties": [
          {
            "timeInPeriod": "16:35",
            "type": "MIN",
            "duration": 2,
            "committedByPlayer": {
              "firstName": {
                "default": "Rasmus"
              },
              "lastName": {
                "default": "Andersson"
              },
              "sweaterNumber": 4
            },
            "teamAbbrev": {
              "default": "CGY"
            },
            "drawnBy": {
              "firstName": {
                "default": "Michael"
              },
              "lastName": {
                "default": "McCarron"
              },
              "sweaterNumber": 47
            },
            "descKey": "tripping"
          }
        ]
      }
    ]
  },
  "clock": {
    "timeRemaining": "00:00",
    "secondsRemaining": 0,
    "running": false,
    "inIntermission": false
  }
}