{
  "id": 2025020205,
  "season": 20252026,
  "gameType": 2,
  "limitedScoring": false,
  "gameDate": "2025-11-04",
  "venue": {
    "default": "UBS Arena"
  },
  "venueLocation": {
    "default": "Elmont"
  },
  "startTimeUTC": "2025-11-05T00:00:00Z",
  "easternUTCOffset": "-05:00",
  "venueUTCOffset": "-05:00",
  "venueTimezone": "America/New_York",
  "periodDescriptor": {
    "number": 5,
    "periodType": "SO",
    "maxRegulationPeriods": 3
  },
  "tvBroadcasts": [
    {
      "id": 31,
      "market": "A",
      "countryCode": "US",
      "network": "NESN",
      "sequenceNumber": 396
    },
    {
      "id": 409,
      "market": "H",
      "countryCode": "US",
      "network": "MSGSN",
      "sequenceNumber": 402
    }
  ],
  "gameState": "OFF",
  "gameScheduleState": "OK",
  "awayTeam": {
    "id": 6,
    "commonName": {
      "default": "Bruins"
    },
    "abbrev": "BOS",
    "placeName": {
      "default": "Boston"
    },
    "placeNameWithPreposition": {
      "default": "Boston",
      "fr": "de Boston"
    },
    "score": 4,
    "sog": 27,
    "logo": "https://assets.nhle.com/logos/nhl/svg/BOS_light.svg?season=20252026",
    "darkLogo": "https://assets.nhle.com/logos/nhl/svg/BOS_dark.svg?season=20252026"
  },
  "homeTeam": {
    "id": 2,
    "commonName": {
      "default": "Islanders"
    },
    "abbrev": "NYI",
    "placeName": {
      "default": "New York"
    },
    "placeNameWithPreposition": {
      "default": "New York",
      "fr": "de New York"
    },
    "score": 3,
    "sog": 33,
    "logo": "https://assets.nhle.com/logos/nhl/svg/NYI_light.svg",
    "darkLogo": "https://assets.nhle.com/logos/nhl/svg/NYI_dark.svg"
  },
  "shootoutInUse": true,
  "maxPeriods": 5,
  "regPeriods": 3,
  "otInUse": true,
  "tiesInUse": false,
  "summary": {
    "scoring": [
      {
        "periodDescriptor": {
          "number": 1,
          "periodType": "REG",
          "maxRegulationPeriods": 3
        },
        "goals": []
      },
      {
        "periodDescriptor": {
          "number": 2,
          "periodType": "REG",
          "maxRegulationPeriods": 3
        },
        "goals": [
          {
            "situationCode": "1551",
            "eventId": 496,
            "strength": "ev",
            "playerId": 8477407,
            "firstName": {
              "default": "Anthony"
            },
            "lastName": {
              "default": "Duclair"
            },
            "name": {
              "default": "A. Duclair"
            },
            "teamAbbrev": {
              "default": "NYI"
            },
            "headshot": "https://assets.nhle.com/mugs/nhl/20252026/NYI/8477407.png",
            "highlightClipSharingUrl": "https://nhl.com/video/bos-nyi-duclair-scores-goal-against-jeremy-swayman-6384528537112",
            "highlightClipSharingUrlFr": "https://nhl.com/fr/video/bos-nyi-duclair-marque-un-but-contre-jeremy-swayman-6384529894112",
            "highlightClip": 6384528537112,
            "highlightClipFr": 6384529894112,
            "discreteClip": 6384527845112,
            "discreteClipFr": 6384529404112,
            "goalsToDate": 3,
            "awayScore": 0,
            "homeScore": 1,
            "leadingTeamAbbrev": {
              "default": "NYI"
            },
            "timeInPeriod": "05:11",
            "shotType": "wrist",
            "goalModifier": "none",
            "assists": [
              {
                "playerId": 8475231,
                "firstName": {
                  "default": "Casey"
                },
                "lastName": {
                  "default": "Cizikas"
                },
                "name": {
                  "default": "C. Cizikas"
                },
                "assistsToDate": 2,
                "sweaterNumber": 53
              },
              {
                "playerId": 8481237,
                "firstName": {
                  "default": "Kyle"
                },
                "lastName": {
                  "default": "MacLean"
                },
                "name": {
                  "default": "K. MacLean"
                },
                "assistsToDate": 1,
                "sweaterNumber": 32
              }
            ],
            "pptReplayUrl": "https://wsr.nhle.com/sprites/20252026/2025020205/ev496.json",
            "homeTeamDefendingSide": "right",
            "isHome": true
          },
          {
            "situationCode": "1551",
            "eventId": 653,
            "strength": "ev",
            "playerId": 8478042,
            "firstName": {
              "default": "Viktor"
            },
            "lastName": {
              "default": "Arvidsson"
            },
            "name": {
              "default": "V. Arvidsson"
            },
            "teamAbbrev": {
              "default": "BOS"
            },
            "headshot": "https://assets.nhle.com/mugs/nhl/20252026/BOS/8478042.png",
            "highlightClipSharingUrl": "https://nhl.com/video/viktor-arvidsson-with-a-goal-vs-new-york-islanders-6384529031112",
            "highlightClipSharingUrlFr": "https://nhl.com/fr/video/bos-nyi-arvidsson-marque-un-but-contre-ilya-sorokin-6384530105112",
            "highlightClip": 6384529031112,
            "highlightClipFr": 6384530105112,
            "discreteClip": 6384529036112,
            "discreteClipFr": 6384530600112,
            "goalsToDate": 4,
            "awayScore": 1,
            "homeScore": 1,
            "timeInPeriod": "12:21",
            "shotType": "wrist",
            "goalModifier": "none",
            "assists": [
              {
                "playerId": 8476854,
                "firstName": {
                  "default": "Hampus"
                },
                "lastName": {
                  "default": "Lindholm"
                },
                "name": {
                  "default": "H. Lindholm"
                },
                "assistsToDate": 2,
                "sweaterNumber": 27
              },
              {
                "playerId": 8479999,
                "firstName": {
                  "default": "Casey"
                },
                "lastName": {
                  "default": "Mittelstadt"
                },
                "name": {
                  "default": "C. Mittelstadt"
                },
                "assistsToDate": 5,
                "sweaterNumber": 11
              }
            ],
            "pptReplayUrl": "https://wsr.nhle.com/sprites/20252026/2025020205/ev653.json",
            "homeTeamDefendingSide": "right",
            "isHome": false
          },
          {
            "situationCode": "1551",
            "eventId": 659,
            "strength": "ev",
            "playerId": 8477500,
            "firstName": {
              "default": "Bo"
            },
            "lastName": {
              "default": "Horvat"
            },
            "name": {
              "default": "B. Horvat"
            },
            "teamAbbrev": {
              "default": "NYI"
            },
            "headshot": "https://assets.nhle.com/mugs/nhl/20252026/NYI/8477500.png",
            "highlightClipSharingUrl": "https://nhl.com/video/bo-horvat-with-a-goal-vs-boston-bruins-6384530223112",
            "highlightClipSharingUrlFr": "https://nhl.com/fr/video/bo-horvat-with-a-goal-vs-les-bruins-de-boston-6384529645112",
            "highlightClip": 6384530223112,
            "highlightClipFr": 6384529645112,
            "discreteClip": 6384530607112,
            "discreteClipFr": 6384531291112,
            "goalsToDate": 8,
            "awayScore": 1,
            "homeScore": 2,
            "leadingTeamAbbrev": {
              "default": "NYI"
            },
            "timeInPeriod": "13:06",
            "shotType": "wrist",
            "goalModifier": "none",
            "assists": [
              {
                "playerId": 8478445,
                "firstName": {
                  "default": "Mathew"
                },
                "lastName": {
                  "default": "Barzal"
                },
                "name": {
                  "default": "M. Barzal"
                },
                "assistsToDate": 7,
                "sweaterNumber": 13
              },
              {
                "playerId": 8482476,
                "firstName": {
                  "default": "Emil"
                },
                "lastName": {
                  "default": "Heineman"
                },
                "name": {
                  "default": "E. Heineman"
                },
                "assistsToDate": 3,
                "sweaterNumber": 51
              }
            ],
            "pptReplayUrl": "https://wsr.nhle.com/sprites/20252026/2025020205/ev659.json",
            "homeTeamDefendingSide": "right",
            "isHome": true
          },
          {
            "situationCode": "1541",
            "eventId": 712,
            "strength": "pp",
            "playerId": 8478401,
            "firstName": {
              "default": "Pavel"
            },
            "lastName": {
              "default": "Zacha"
            },
            "name": {
              "default": "P. Zacha"
            },
            "teamAbbrev": {
              "default": "BOS"
            },
            "headshot": "https://assets.nhle.com/mugs/nhl/20252026/BOS/8478401.png",
            "highlightClipSharingUrl": "https://nhl.com/video/bos-nyi-zacha-scores-ppg-against-ilya-sorokin-6384531496112",
            "highlightClipSharingUrlFr": "https://nhl.com/fr/video/bos-nyi-zacha-marque-un-but-en-a-n-contre-ilya-sorokin-6384531990112",
            "highlightClip": 6384531496112,
            "highlightClipFr": 6384531990112,
            "discreteClip": 6384530909112,
            "discreteClipFr": 6384530334112,
            "goalsToDate": 3,
            "awayScore": 2,
            "homeScore": 2,
            "timeInPeriod": "17:29",
            "shotType": "wrist",
            "goalModifier": "none",
            "assists": [
              {
                "playerId": 8479325,
                "firstName": {
                  "default": "Charlie"
                },
                "lastName": {
                  "default": "McAvoy"
                },
                "name": {
                  "default": "C. McAvoy"
                },
                "assistsToDate": 11,
                "sweaterNumber": 73
              },
              {
                "playerId": 8479987,
                "firstName": {
                  "default": "Morgan"
                },
                "lastName": {
                  "default": "Geekie"
                },
                "name": {
                  "default": "M. Geekie"
                },
                "assistsToDate": 3,
                "sweaterNumber": 39
              }
            ],
            "pptReplayUrl": "https://wsr.nhle.com/sprites/20252026/2025020205/ev712.json",
            "homeTeamDefendingSide": "right",
            "isHome": false
          }
        ]
      },
      {
        "periodDescriptor": {
          "number": 3,
          "periodType": "REG",
          "maxRegulationPeriods": 3
        },
        "goals": [
          {
            "situationCode": "1551",
            "eventId": 966,
            "strength": "ev",
            "playerId": 8477500,
            "firstName": {
              "default": "Bo"
            },
            "lastName": {
              "default": "Horvat"
            },
            "name": {
              "default": "B. Horvat"
            },
            "teamAbbrev": {
              "default": "NYI"
            },
            "headshot": "https://assets.nhle.com/mugs/nhl/20252026/NYI/8477500.png",
            "highlightClipSharingUrl": "https://nhl.com/video/bos-nyi-horvat-scores-goal-against-jeremy-swayman-6384532899112",
            "highlightClipSharingUrlFr": "https://nhl.com/fr/video/bos-nyi-horvat-marque-un-but-contre-jeremy-swayman-6384531436112",
            "highlightClip": 6384532899112,
            "highlightClipFr": 6384531436112,
            "discreteClip": 6384531350112,
            "discreteClipFr": 6384531239112,
            "goalsToDate": 9,
            "awayScore": 2,
            "homeScore": 3,
            "leadingTeamAbbrev": {
              "default": "NYI"
            },
            "timeInPeriod": "05:05",
            "shotType": "wrist",
            "goalModifier": "none",
            "assists": [
              {
                "playerId": 8485366,
                "firstName": {
                  "default": "Matthew"
                },
                "lastName": {
                  "default": "Schaefer"
                },
                "name": {
                  "default": "M. Schaefer"
                },
                "assistsToDate": 6,
                "sweaterNumber": 48
              },
              {
                "playerId": 8475151,
                "firstName": {
                  "default": "Kyle"
                },
                "lastName": {
                  "default": "Palmieri"
                },
                "name": {
                  "default": "K. Palmieri"
                },
                "assistsToDate": 6,
                "sweaterNumber": 21
              }
            ],
            "pptReplayUrl": "https://wsr.nhle.com/sprites/20252026/2025020205/ev966.json",
            "homeTeamDefendingSide": "left",
            "isHome": true
          },
          {
            "situationCode": "1551",
            "eventId": 1103,
            "strength": "ev",
            "playerId": 8482177,
            "firstName": {
              "default": "Marat"
            },
            "lastName": {
              "default": "Khusnutdinov",
              "cs": "Chusnutdinov",
              "fi": "Husnutdinov",
              "sk": "Chusnutdinov"
            },
            "name": {
              "default": "M. Khusnutdinov",
              "cs": "M. Chusnutdinov",
              "fi": "M. Husnutdinov",
              "sk": "M. Chusnutdinov"
            },
            "teamAbbrev": {
              "default": "BOS"
            },
            "headshot": "https://assets.nhle.com/mugs/nhl/20252026/BOS/8482177.png",
            "highlightClipSharingUrl": "https://nhl.com/video/marat-khusnutdinov-with-a-goal-vs-new-york-islanders-6384532820112",
            "highlightClipSharingUrlFr": "https://nhl.com/fr/video/marat-khusnutdinov-with-a-goal-vs-les-islanders-de-new-york-6384533324112",
            "highlightClip": 6384532820112,
            "highlightClipFr": 6384533324112,
            "discreteClip": 6384532823112,
            "discreteClipFr": 6384532928112,
            "goalsToDate": 2,
            "awayScore": 3,
            "homeScore": 3,
            "timeInPeriod": "15:06",
            "shotType": "backhand",
            "goalModifier": "none",
            "assists": [
              {
                "playerId": 8483489,
                "firstName": {
                  "default": "Fraser"
                },
                "lastName": {
                  "default": "Minten"
                },
                "name": {
                  "default": "F. Minten"
                },
                "assistsToDate": 3,
                "sweaterNumber": 93
              },
              {
                "playerId": 8477956,
                "firstName": {
                  "default": "David"
                },
                "lastName": {
                  "default": "Pastrnak",
                  "cs": "Pastrňák",
                  "sk": "Pastrňák"
                },
                "name": {
                  "default": "D. Pastrnak",
                  "cs": "D. Pastrňák",
                  "sk": "D. Pastrňák"
                },
                "assistsToDate": 11,
                "sweaterNumber": 88
              }
            ],
            "pptReplayUrl": "https://wsr.nhle.com/sprites/20252026/2025020205/ev1103.json",
            "homeTeamDefendingSide": "left",
            "isHome": false
          }
        ]
      },
      {
        "periodDescriptor": {
          "number": 4,
          "periodType": "OT",
          "maxRegulationPeriods": 3
        },
        "goals": []
      },
      {
        "periodDescriptor": {
          "number": 5,
          "periodType": "SO",
          "maxRegulationPeriods": 3
        },
        "goals": [
          {
            "situationCode": "0101",
            "eventId": 857,
            "strength": "ev",
            "playerId": 8482177,
            "firstName": {
              "default": "Marat"
            },
            "lastName": {
              "default": "Khusnutdinov",
              "cs": "Chusnutdinov",
              "fi": "Husnutdinov",
              "sk": "Chusnutdinov"
            },
            "name": {
              "default": "M. Khusnutdinov",
              "cs": "M. Chusnutdinov",
              "fi": "M. Husnutdinov",
              "sk": "M. Chusnutdinov"
            },
            "teamAbbrev": {
              "default": "BOS"
            },
            "headshot": "https://assets.nhle.com/mugs/nhl/20252026/BOS/8482177.png",
            "discreteClip": 6384535553112,
            "discreteClipFr": 6384533940112,
            "awayScore": 4,
            "homeScore": 3,
            "leadingTeamAbbrev": {
              "default": "BOS"
            },
            "timeInPeriod": "00:00",
            "shotType": "snap",
            "goalModifier": "none",
            "assists": [],
            "homeTeamDefendingSide": "left",
            "isHome": false
          }
        ]
      }
    ],
    "shootout": [
      {
        "sequence": 1,
        "playerId": 8481601,
        "teamAbbrev": {
          "default": "NYI"
        },
        "firstName": {
          "default": "Simon"
        },
        "lastName": {
          "default": "Holmstrom",
          "cs": "Holmström",
          "fi": "Holmström",
          "sk": "Holmström",
          "sv": "Holmström"
        },
        "shotType": "wrist",
        "result": "save",
        "headshot": "https://assets.nhle.com/mugs/nhl/20252026/NYI/8481601.png",
        "gameWinner": false
      },
      {
        "sequence": 2,
        "playerId": 8479999,
        "teamAbbrev": {
          "default": "BOS"
        },
        "firstName": {
          "default": "Casey"
        },
        "lastName": {
          "default": "Mittelstadt"
        },
        "shotType": "backhand",
        "result": "save",
        "headshot": "https://assets.nhle.com/mugs/nhl/20252026/BOS/8479999.png",
        "gameWinner": false
      },
      {
        "sequence": 3,
        "playerId": 8477500,
        "teamAbbrev": {
          "default": "NYI"
        },
        "firstName": {
          "default": "Bo"
        },
        "lastName": {
          "default": "Horvat"
        },
        "shotType": "snap",
        "result": "save",
        "headshot": "https://assets.nhle.com/mugs/nhl/20252026/NYI/8477500.png",
        "gameWinner": false
      },
      {
        "sequence": 4,
        "playerId": 8482177,
        "teamAbbrev": {
          "default": "BOS"
        },
        "firstName": {
          "default": "Marat"
        },
        "lastName": {
          "default": "Khusnutdinov",
          "cs": "Chusnutdinov",
          "fi": "Husnutdinov",
          "sk": "Chusnutdinov"
        },
        "shotType": "snap",
        "result": "goal",
        "headshot": "https://assets.nhle.com/mugs/nhl/20252026/BOS/8482177.png",
        "gameWinner": true,
        "discreteClip": 6384535553112,
        "discreteClipFr": 6384533940112
      },
      {
        "sequence": 5,
        "playerId": 8477494,
        "teamAbbrev": {
          "default": "NYI"
        },
        "firstName": {
          "default": "Jonathan"
        },
        "lastName": {
          "default": "Drouin"
        },
        "shotType": "wrist",
        "result": "save",
        "headshot": "https://assets.nhle.com/mugs/nhl/20252026/NYI/8477494.png",
        "gameWinner": false
      }
    ],
    "threeStars": [
      {
        "star": 1,
        "playerId": 8482177,
        "teamAbbrev": "BOS",
        "headshot": "https://assets.nhle.com/mugs/nhl/20252026/BOS/8482177.png",
        "name": {
          "default": "M. Khusnutdinov",
          "cs": "M. Chusnutdinov",
          "fi": "M. Husnutdinov",
          "sk": "M. Chusnutdinov"
        },
        "sweaterNo": 92,
        "position": "C",
        "goals": 1,
        "assists": 0,
        "points": 1
      },
      {
        "star": 2,
        "playerId": 8477500,
        "teamAbbrev": "NYI",
        "headshot": "https://assets.nhle.com/mugs/nhl/20252026/NYI/8477500.png",
        "name": {
          "default": "B. Horvat"
        },
        "sweaterNo": 14,
        "position": "C",
        "goals": 2,
        "assists": 0,
        "points": 2
      },
      {
        "star": 3,
        "playerId": 8480280,
        "teamAbbrev": "BOS",
        "headshot": "https://assets.nhle.com/mugs/nhl/20252026/BOS/8480280.png",
        "name": {
          "default": "J. Swayman"
        },
        "sweaterNo": 1,
        "position": "G",
        "goalsAgainstAverage": 2.77,
        "savePctg": 0.909
      }
    ],
    "penalties": [
      {
        "periodDescriptor": {
          "number": 1,
          "periodType": "REG",
          "maxRegulationPeriods": 3
        },
        "penalties": []
      },
      {
        "periodDescriptor": {
          "number": 2,
          "periodType": "REG",
          "maxRegulationPeriods": 3
        },
        "penalties": [
          {
            "timeInPeriod": "01:10",
            "type": "MIN",
            "duration": 2,
            "committedByPlayer": {
              "firstName": {
                "default": "Nikita"
              },
              "lastName": {
                "default": "Zadorov"
              },
              "sweaterNumber": 91
            },
            "teamAbbrev": {
              "default": "BOS"
            },
            "drawnBy": {
              "firstName": {
                "default": "Anders"
              },
              "lastName": {
                "default": "Lee"
              },
              "sweaterNumber": 27
            },
            "descKey": "tripping"
          },
          {
            "timeInPeriod": "06:17",
            "type": "MIN",
            "duration": 2,
            "committedByPlayer": {
              "firstName": {
                "default": "Mathew"
              },
              "lastName": {
                "default": "Barzal"
              },
              "sweaterNumber": 13
            },
            "teamAbbrev": {
              "default": "NYI"
            },
            "drawnBy": {
              "firstName": {
                "default": "Marat"
              },
              "lastName": {
                "default": "Khusnutdinov",
                "cs": "Chusnutdinov",
                "fi": "Husnutdinov",
                "sk": "Chusnutdinov"
              },
              "sweaterNumber": 92
            },
            "descKey": "holding"
          },
          {
            "timeInPeriod": "09:18",
            "type": "MIN",
            "duration": 2,
            "committedByPlayer": {
              "firstName": {
                "default": "Nikita"
              },
              "lastName": {
                "default": "Zadorov"
              },
              "sweaterNumber": 91
            },
            "teamAbbrev": {
              "default": "BOS"
            },
            "drawnBy": {
              "firstName": {
                "default": "Matthew"
              },
              "lastName": {
                "default": "Schaefer"
              },
              "sweaterNumber": 48
            },
            "descKey": "roughing",
            "servedBy": {
              "default": "V. Arvidsson"
            }
          },
          {
            "timeInPeriod": "09:18",
            "type": "MIN",
            "duration": 2,
            "committedByPlayer": {
              "firstName": {
                "default": "Nikita"
              },
              "lastName": {
                "default": "Zadorov"
              },
              "sweaterNumber": 91
            },
            "teamAbbrev": {
              "default": "BOS"
            },
            "drawnBy": {
              "firstName": {
                "default": "Anders"
              },
              "lastName": {
                "default": "Lee"
              },
              "sweaterNumber": 27
            },
            "descKey": "roughing"
          },
          {
            "timeInPeriod": "09:18",
            "type": "MIN",
            "duration": 2,
            "committedByPlayer": {
              "firstName": {
                "default": "Nikita"
              },
              "lastName": {
                "default": "Zadorov"
              },
              "sweaterNumber": 91
            },
            "teamAbbrev": {
              "default": "BOS"
            },
            "drawnBy": {
              "firstName": {
                "default": "Matthew"
              },
              "lastName": {
                "default": "Schaefer"
              },
              "sweaterNumber": 48
            },
            "descKey": "interference"
          },
          {
            "timeInPeriod": "09:18",
            "type": "MIN",
            "duration": 2,
            "committedByPlayer": {
              "firstName": {
                "default": "Anthony"
              },
              "lastName": {
                "default": "Duclair"
              },
              "sweaterNumber": 11
            },
            "teamAbbrev": {
              "default": "NYI"
            },
            "drawnBy": {
              "firstName": {
                "default": "Nikita"
              },
              "lastName": {
                "default": "Zadorov"
              },
              "sweaterNumber": 91
            },
            "descKey": "roughing"
          },
          {
            "timeInPeriod": "09:18",
            "type": "MIN",
            "duration": 2,
            "committedByPlayer": {
              "firstName": {
                "default": "Anders"
              },
              "lastName": {
                "default": "Lee"
              },
              "sweaterNumber": 27
            },
            "teamAbbrev": {
              "default": "NYI"
            },
            "drawnBy": {
              "firstName": {
                "default": "Nikita"
              },
              "lastName": {
                "default": "Zadorov"
              },
              "sweaterNumber": 91
            },
            "descKey": "roughing"
          },
          {
            "timeInPeriod": "16:45",
            "type": "MIN",
            "duration": 2,
            "committedByPlayer": {
              "firstName": {
                "default": "Anders"
              },
              "lastName": {
                "default": "Lee"
              },
              "sweaterNumber": 27
            },
            "teamAbbrev": {
              "default": "NYI"
            },
            "drawnBy": {
              "firstName": {
                "default": "Fraser"
              },
              "lastName": {
                "default": "Minten"
              },
              "sweaterNumber": 93
            },
            "descKey": "cross-checking"
          },
          {
            "timeInPeriod": "17:43",
            "type": "MIN",
            "duration": 2,
            "committedByPlayer": {
              "firstName": {
                "default": "Scott"
              },
              "lastName": {
                "default": "Mayfield"
              },
              "sweaterNumber": 24
            },
            "teamAbbrev": {
              "default": "NYI"
            },
            "drawnBy": {
              "firstName": {
                "default": "Michael"
              },
              "lastName": {
                "default": "Eyssimont"
              },
              "sweaterNumber": 81
            },
            "descKey": "cross-checking"
          }
        ]
      },
      {
        "periodDescriptor": {
          "number": 3,
          "periodType": "REG",
          "maxRegulationPeriods": 3
        },
        "penalties": [
          {
            "timeInPeriod": "02:56",
            "type": "MIN",
            "duration": 2,
            "committedByPlayer": {
              "firstName": {
                "default": "Matthew"
              },
              "lastName": {
                "default": "Schaefer"
              },
              "sweaterNumber": 48
            },
            "teamAbbrev": {
              "default": "NYI"
            },
            "drawnBy": {
              "firstName": {
                "default": "Mark"
              },
              "lastName": {
                "default": "Kastelic"
              },
              "sweaterNumber": 47
            },
            "descKey": "cross-checking"
          },
          {
            "timeInPeriod": "18:16",
            "type": "MIN",
            "duration": 2,
            "committedByPlayer": {
              "firstName": {
                "default": "Charlie"
              },
              "lastName": {
                "default": "McAvoy"
              },
              "sweaterNumber": 73
            },
            "teamAbbrev": {
              "default": "BOS"
            },
            "drawnBy": {
              "firstName": {
                "default": "Jonathan"
              },
              "lastName": {
                "default": "Drouin"
              },
              "sweaterNumber": 29
            },
            "descKey": "high-sticking"
          }
        ]
      },
      {
        "periodDescriptor": {
          "number": 4,
          "periodType": "OT",
          "maxRegulationPeriods": 3
        },
        "penalties": []
      }
    ]
  },
  "clock": {
    "timeRemaining": "00:00",
    "secondsRemaining": 0,
    "running": false,
    "inIntermission": false
  }
}